{
  "authors": [],
  "claims_path": "kb/normalized/claims/table-tr-td-td-td-colspan-3-technische-mitteilung-td-td-colspan-2-tm-hl-255.jsonl",
  "date_text": "April 1974",
  "doc_id": "table-tr-td-td-td-colspan-3-technische-mitteilung-td-td-colspan-2-tm-hl-255",
  "document_type": "report",
  "entities": {},
  "figures": [],
  "file_hash": "9df062184950de8db329417262b8bb6c4fbcadc1529e5a1fe87770eb507648b0",
  "markdown_path": "pdf/EIR-TM-HL-255/EIR-TM-HL-255/hybrid_ocr/EIR-TM-HL-255.md",
  "report_number": null,
  "report_numbers": [],
  "report_series": "eir-series",
  "section_count": 8,
  "sections": [
    {
      "anchor": "literatur",
      "end_line": 57,
      "heading": "Literatur",
      "level": 1,
      "start_line": 56
    },
    {
      "anchor": "1-j-cherry",
      "end_line": 61,
      "heading": "(1) J. Cherry",
      "level": 2,
      "start_line": 58
    },
    {
      "anchor": "2-w-davies-m-townsend",
      "end_line": 65,
      "heading": "(2) W. Davies, M. Townsend",
      "level": 2,
      "start_line": 62
    },
    {
      "anchor": "3-r-kaiser-g-gottschalk",
      "end_line": 73,
      "heading": "(3) R. Kaiser, G. Gottschalk",
      "level": 2,
      "start_line": 66
    },
    {
      "anchor": "1-prinzip",
      "end_line": 77,
      "heading": "1. Prinzip",
      "level": 1,
      "start_line": 74
    },
    {
      "anchor": "2-reagentien",
      "end_line": 91,
      "heading": "2. Reagentien",
      "level": 1,
      "start_line": 78
    },
    {
      "anchor": "3-apparatur",
      "end_line": 106,
      "heading": "3. Apparatur",
      "level": 1,
      "start_line": 92
    },
    {
      "anchor": "4-durchf-hrung",
      "end_line": 118,
      "heading": "4. Durchführung",
      "level": 1,
      "start_line": 107
    }
  ],
  "source_dir": "pdf/EIR-TM-HL-255",
  "tables": [],
  "title": "<table><tr><td></td><td colspan=\"3\">Technische Mitteilung</td><td colspan=\"2\">TM-HL-255",
  "topics": [
    "instrumentation-and-controls"
  ],
  "warnings": [
    "authors_not_detected",
    "report_number_not_detected"
  ]
}