{
  "alloy-material": [
    {
      "count": 73,
      "line_hits": [
        129,
        139,
        220,
        250,
        291,
        312,
        340,
        398,
        406,
        439,
        459,
        465,
        621,
        631,
        751,
        773,
        779,
        783,
        851,
        853,
        859,
        869,
        871,
        873,
        884,
        887,
        905,
        907,
        911,
        912,
        924,
        936,
        981,
        983,
        987,
        993,
        1081,
        1192,
        1196,
        1210,
        1264,
        1266,
        1270,
        1272,
        1274,
        1300,
        1302,
        1313,
        1328,
        1333
      ],
      "name": "graphite"
    },
    {
      "count": 37,
      "line_hits": [
        241,
        243,
        261,
        265,
        267,
        269,
        271,
        670,
        678,
        680,
        773,
        779,
        831,
        859,
        955,
        1081,
        1095,
        1525,
        1635,
        1780,
        1794,
        1796,
        1803,
        1805,
        1809,
        1811,
        1813,
        1815,
        1817,
        1822,
        1826,
        1829,
        1839,
        1843,
        1849,
        1858,
        1875
      ],
      "name": "Hastelloy N"
    },
    {
      "count": 29,
      "line_hits": [
        1196,
        1210,
        1218,
        1232,
        1234,
        1236,
        1238,
        1240,
        1242,
        1246,
        1248,
        1250,
        1252,
        1254,
        1256,
        1264,
        1268,
        1274,
        1287,
        1288,
        1303,
        1519,
        1525,
        1736,
        1737,
        1794,
        1798,
        1805,
        1807
      ],
      "name": "molybdenum"
    },
    {
      "count": 19,
      "line_hits": [
        261,
        670,
        1216,
        1218,
        1220,
        1230,
        1250,
        1420,
        1493,
        1501,
        1523,
        1549,
        1575,
        1727,
        1780,
        1794,
        1798,
        1803,
        1833
      ],
      "name": "nickel"
    },
    {
      "count": 16,
      "line_hits": [
        305,
        670,
        672,
        1184,
        1230,
        1378,
        1380,
        1420,
        1511,
        1513,
        1535,
        1539,
        1541,
        1567,
        1572,
        1594
      ],
      "name": "zirconium"
    },
    {
      "count": 10,
      "line_hits": [
        269,
        777,
        1798,
        1811,
        1817,
        1820,
        1822,
        1824,
        1843,
        1847
      ],
      "name": "niobium"
    },
    {
      "count": 9,
      "line_hits": [
        265,
        269,
        271,
        1798,
        1807,
        1811,
        1817,
        1822,
        1847
      ],
      "name": "titanium"
    },
    {
      "count": 6,
      "line_hits": [
        384,
        443,
        1055,
        1527,
        1736,
        1826
      ],
      "name": "beryllium"
    },
    {
      "count": 1,
      "line_hits": [
        1727
      ],
      "name": "Hastelloy B"
    },
    {
      "count": 1,
      "line_hits": [
        1809
      ],
      "name": "Inconel 601"
    },
    {
      "count": 1,
      "line_hits": [
        1671
      ],
      "name": "stainless steel 316"
    },
    {
      "count": 1,
      "line_hits": [
        271
      ],
      "name": "titanium-modified Hastelloy-N"
    }
  ],
  "component": [
    {
      "count": 25,
      "line_hits": [
        279,
        281,
        295,
        449,
        451,
        457,
        459,
        827,
        831,
        1021,
        1065,
        1095,
        1099,
        1210,
        1212,
        1254,
        1256,
        1260,
        1264,
        1278,
        1294,
        1525,
        1859,
        1860,
        1861
      ],
      "name": "loop"
    },
    {
      "count": 18,
      "line_hits": [
        246,
        505,
        520,
        522,
        550,
        566,
        567,
        589,
        595,
        692,
        753,
        797,
        1005,
        1007,
        1027,
        1047,
        1091,
        1570
      ],
      "name": "off-gas system"
    },
    {
      "count": 13,
      "line_hits": [
        443,
        473,
        475,
        505,
        524,
        526,
        550,
        568,
        569,
        589,
        595,
        775,
        1099
      ],
      "name": "pump"
    },
    {
      "count": 13,
      "line_hits": [
        279,
        293,
        352,
        451,
        455,
        469,
        499,
        515,
        518,
        561,
        564,
        785,
        805
      ],
      "name": "steam generator"
    },
    {
      "count": 9,
      "line_hits": [
        291,
        441,
        528,
        570,
        621,
        805,
        807,
        841,
        1364
      ],
      "name": "heat exchanger"
    },
    {
      "count": 8,
      "line_hits": [
        441,
        481,
        505,
        536,
        550,
        574,
        589,
        595
      ],
      "name": "control rod"
    },
    {
      "count": 7,
      "line_hits": [
        441,
        471,
        473,
        505,
        550,
        589,
        595
      ],
      "name": "salt pump"
    },
    {
      "count": 4,
      "line_hits": [
        483,
        625,
        627,
        631
      ],
      "name": "drain tank"
    },
    {
      "count": 3,
      "line_hits": [
        443,
        477,
        479
      ],
      "name": "freeze valve"
    },
    {
      "count": 2,
      "line_hits": [
        779,
        1782
      ],
      "name": "graphite moderator"
    },
    {
      "count": 2,
      "line_hits": [
        1035,
        1681
      ],
      "name": "sampler"
    },
    {
      "count": 1,
      "line_hits": [
        625
      ],
      "name": "intermediate heat exchanger"
    }
  ],
  "organization": [
    {
      "count": 139,
      "line_hits": [
        11,
        25,
        59,
        348,
        349,
        350,
        351,
        353,
        354,
        355,
        402,
        420,
        421,
        423,
        424,
        425,
        435,
        455,
        495,
        496,
        497,
        498,
        500,
        501,
        647,
        648,
        690,
        715,
        1029,
        1232,
        1236,
        1256,
        1420,
        1629,
        1630,
        1631,
        1632,
        1633,
        1634,
        1635,
        1637,
        1638,
        1639,
        1648,
        1649,
        1650,
        1651,
        1652,
        1653,
        1654
      ],
      "name": "ORNL"
    },
    {
      "count": 4,
      "line_hits": [
        257,
        1642,
        1645,
        1663
      ],
      "name": "AEC"
    },
    {
      "count": 4,
      "line_hits": [
        293,
        352,
        455,
        499
      ],
      "name": "Foster Wheeler"
    },
    {
      "count": 2,
      "line_hits": [
        1727,
        2036
      ],
      "name": "ANL"
    },
    {
      "count": 2,
      "line_hits": [
        65,
        422
      ],
      "name": "Union Carbide"
    }
  ],
  "reactor": [
    {
      "count": 150,
      "line_hits": [
        231,
        237,
        241,
        245,
        246,
        250,
        253,
        263,
        279,
        281,
        336,
        367,
        386,
        392,
        397,
        404,
        412,
        414,
        416,
        431,
        451,
        453,
        459,
        465,
        467,
        477,
        479,
        481,
        489,
        491,
        509,
        555,
        615,
        635,
        639,
        643,
        660,
        662,
        666,
        672,
        698,
        706,
        713,
        715,
        721,
        725,
        739,
        745,
        747,
        749
      ],
      "name": "ARE"
    },
    {
      "count": 120,
      "line_hits": [
        157,
        193,
        233,
        253,
        281,
        293,
        305,
        310,
        312,
        316,
        318,
        348,
        355,
        394,
        404,
        406,
        421,
        422,
        424,
        425,
        431,
        435,
        439,
        453,
        455,
        457,
        463,
        469,
        475,
        483,
        495,
        496,
        500,
        615,
        643,
        647,
        648,
        658,
        660,
        662,
        670,
        672,
        674,
        680,
        692,
        698,
        700,
        702,
        704,
        706
      ],
      "name": "MSBR"
    },
    {
      "count": 114,
      "line_hits": [
        95,
        197,
        299,
        301,
        303,
        305,
        308,
        310,
        312,
        314,
        318,
        320,
        353,
        379,
        384,
        386,
        388,
        394,
        400,
        406,
        412,
        414,
        420,
        431,
        439,
        461,
        463,
        465,
        467,
        469,
        489,
        534,
        546,
        573,
        579,
        583,
        589,
        595,
        615,
        621,
        623,
        627,
        629,
        639,
        643,
        658,
        662,
        666,
        672,
        674
      ],
      "name": "DMSR"
    },
    {
      "count": 47,
      "line_hits": [
        155,
        233,
        261,
        265,
        267,
        285,
        435,
        443,
        469,
        473,
        477,
        615,
        670,
        678,
        680,
        743,
        755,
        757,
        769,
        771,
        775,
        777,
        779,
        807,
        859,
        1003,
        1027,
        1029,
        1031,
        1033,
        1035,
        1043,
        1045,
        1047,
        1061,
        1065,
        1089,
        1420,
        1527,
        1656,
        1681,
        1688,
        1755,
        1794,
        1809,
        1813,
        1815
      ],
      "name": "MSRE"
    },
    {
      "count": 3,
      "line_hits": [
        245,
        246,
        250
      ],
      "name": "MSBE"
    },
    {
      "count": 2,
      "line_hits": [
        1732,
        1743
      ],
      "name": "LMFR"
    }
  ],
  "reactor-concept": [
    {
      "count": 1,
      "line_hits": [
        1732
      ],
      "name": "fluid-fuel reactor"
    }
  ],
  "report-series": [
    {
      "count": 50,
      "line_hits": [
        1648,
        1649,
        1650,
        1651,
        1652,
        1662,
        1669,
        1672,
        1673,
        1674,
        1675,
        1682,
        1684,
        1685,
        1686,
        1689,
        1692,
        1693,
        1695,
        1697,
        1698,
        1701,
        1704,
        1705,
        1706,
        1707,
        1708,
        1709,
        1710,
        1711,
        1713,
        1714,
        1715,
        1716,
        1718,
        1728,
        1729,
        1731,
        1739,
        1744,
        1745,
        1747,
        1748,
        1749,
        1750,
        1761,
        1765,
        1771,
        1773,
        1774
      ],
      "name": "MSR Program Semiannual Progress Report"
    },
    {
      "count": 1,
      "line_hits": [
        1732
      ],
      "name": "Fluid Fuel Reactors"
    }
  ],
  "salt-system": [
    {
      "count": 36,
      "line_hits": [
        621,
        723,
        747,
        749,
        757,
        799,
        807,
        853,
        1029,
        1079,
        1095,
        1190,
        1191,
        1212,
        1230,
        1232,
        1260,
        1262,
        1282,
        1297,
        1327,
        1362,
        1420,
        1422,
        1424,
        1444,
        1468,
        1635,
        1636,
        1643,
        1653,
        1655,
        1670,
        1691,
        1702,
        1794
      ],
      "name": "fluoride salt"
    },
    {
      "count": 33,
      "line_hits": [
        688,
        698,
        700,
        702,
        706,
        711,
        715,
        725,
        727,
        745,
        749,
        753,
        799,
        871,
        892,
        1023,
        1061,
        1065,
        1067,
        1073,
        1095,
        1184,
        1212,
        1260,
        1388,
        1406,
        1408,
        1468,
        1503,
        1547,
        1556,
        1566,
        1733
      ],
      "name": "LiF"
    },
    {
      "count": 15,
      "line_hits": [
        279,
        281,
        443,
        451,
        453,
        457,
        692,
        807,
        821,
        823,
        827,
        837,
        967,
        969,
        1087
      ],
      "name": "NaBF4-NaF"
    },
    {
      "count": 15,
      "line_hits": [
        285,
        692,
        787,
        807,
        819,
        823,
        825,
        831,
        841,
        896,
        899,
        1022,
        1061,
        1089,
        1382
      ],
      "name": "NaF"
    },
    {
      "count": 2,
      "line_hits": [
        384,
        443
      ],
      "name": "BeF2"
    },
    {
      "count": 2,
      "line_hits": [
        807,
        1283
      ],
      "name": "chloride salt"
    },
    {
      "count": 1,
      "line_hits": [
        1636
      ],
      "name": "UF4"
    }
  ]
}