{
  "alloy-material": [
    {
      "count": 4,
      "line_hits": [
        120,
        126,
        184,
        252
      ],
      "name": "Hastelloy N"
    },
    {
      "count": 1,
      "line_hits": [
        432
      ],
      "name": "stainless steel 304"
    }
  ],
  "component": [
    {
      "count": 1,
      "line_hits": [
        114
      ],
      "name": "heat exchanger"
    }
  ],
  "organization": [
    {
      "count": 20,
      "line_hits": [
        22,
        24,
        38,
        52,
        380,
        381,
        383,
        384,
        392,
        393,
        975,
        976,
        977,
        978,
        979,
        980,
        981,
        982,
        984,
        985
      ],
      "name": "AEC"
    },
    {
      "count": 12,
      "line_hits": [
        20,
        42,
        380,
        381,
        383,
        384,
        392,
        393,
        401,
        777,
        983,
        986
      ],
      "name": "ORNL"
    },
    {
      "count": 2,
      "line_hits": [
        137,
        422
      ],
      "name": "General Electric"
    },
    {
      "count": 2,
      "line_hits": [
        22,
        48
      ],
      "name": "Union Carbide"
    }
  ],
  "reactor": [
    {
      "count": 23,
      "line_hits": [
        120,
        137,
        139,
        141,
        163,
        167,
        173,
        180,
        186,
        224,
        250,
        252,
        257,
        259,
        261,
        279,
        310,
        318,
        329,
        351,
        370,
        569,
        571
      ],
      "name": "ARE"
    },
    {
      "count": 2,
      "line_hits": [
        84,
        980
      ],
      "name": "MSBR"
    },
    {
      "count": 1,
      "line_hits": [
        393
      ],
      "name": "MSRE"
    }
  ],
  "salt-system": [
    {
      "count": 7,
      "line_hits": [
        84,
        120,
        383,
        430,
        798,
        804,
        808
      ],
      "name": "LiF"
    },
    {
      "count": 6,
      "line_hits": [
        9,
        30,
        76,
        120,
        370,
        798
      ],
      "name": "fluoride salt"
    },
    {
      "count": 2,
      "line_hits": [
        798,
        808
      ],
      "name": "BeF2"
    },
    {
      "count": 2,
      "line_hits": [
        798,
        808
      ],
      "name": "FLiBe"
    },
    {
      "count": 2,
      "line_hits": [
        798,
        808
      ],
      "name": "LiF-BeF2-ThF4-UF4"
    },
    {
      "count": 2,
      "line_hits": [
        798,
        808
      ],
      "name": "ThF4"
    },
    {
      "count": 2,
      "line_hits": [
        798,
        808
      ],
      "name": "UF4"
    },
    {
      "count": 1,
      "line_hits": [
        383
      ],
      "name": "KF"
    }
  ]
}