{
  "alloy-material": [
    {
      "count": 31,
      "line_hits": [
        41,
        45,
        51,
        60,
        63,
        74,
        80,
        87,
        91,
        94,
        174,
        195,
        196,
        237,
        259,
        280,
        288,
        330,
        332,
        334,
        341,
        345,
        358,
        362,
        375,
        400,
        404,
        417,
        422,
        468,
        477
      ],
      "name": "stainless steel 304"
    },
    {
      "count": 29,
      "line_hits": [
        41,
        45,
        51,
        60,
        65,
        74,
        83,
        85,
        87,
        139,
        195,
        225,
        263,
        276,
        280,
        288,
        304,
        332,
        345,
        352,
        358,
        362,
        365,
        374,
        377,
        406,
        424,
        446,
        455
      ],
      "name": "stainless steel 316"
    },
    {
      "count": 2,
      "line_hits": [
        67,
        265
      ],
      "name": "molybdenum"
    },
    {
      "count": 2,
      "line_hits": [
        67,
        263
      ],
      "name": "nickel"
    },
    {
      "count": 1,
      "line_hits": [
        67
      ],
      "name": "graphite"
    }
  ],
  "component": [
    {
      "count": 34,
      "line_hits": [
        13,
        41,
        45,
        47,
        51,
        54,
        56,
        67,
        74,
        85,
        87,
        91,
        265,
        267,
        278,
        280,
        284,
        288,
        300,
        304,
        330,
        332,
        345,
        347,
        350,
        352,
        358,
        362,
        365,
        375,
        377,
        396,
        400,
        406
      ],
      "name": "loop"
    }
  ],
  "organization": [
    {
      "count": 5,
      "line_hits": [
        3,
        9,
        23,
        369,
        385
      ],
      "name": "ORNL"
    },
    {
      "count": 1,
      "line_hits": [
        373
      ],
      "name": "Martin Marietta"
    },
    {
      "count": 1,
      "line_hits": [
        23
      ],
      "name": "Union Carbide"
    }
  ],
  "reactor": [
    {
      "count": 22,
      "line_hits": [
        47,
        54,
        65,
        74,
        87,
        89,
        91,
        261,
        265,
        267,
        282,
        300,
        304,
        306,
        332,
        334,
        341,
        345,
        352,
        358,
        404,
        422
      ],
      "name": "ARE"
    }
  ],
  "salt-system": [
    {
      "count": 1,
      "line_hits": [
        386
      ],
      "name": "fluoride salt"
    }
  ]
}