{
  "alloy-material": [
    {
      "count": 18,
      "line_hits": [
        768,
        819,
        843,
        845,
        854,
        858,
        884,
        1799,
        1849,
        1863,
        1967,
        2065,
        2133,
        2291,
        2298,
        2314,
        2338,
        2373
      ],
      "name": "beryllium"
    }
  ],
  "component": [
    {
      "count": 8,
      "line_hits": [
        911,
        980,
        984,
        1000,
        1006,
        1064,
        1709,
        1723
      ],
      "name": "pump"
    },
    {
      "count": 7,
      "line_hits": [
        760,
        766,
        776,
        827,
        1037,
        1045,
        2387
      ],
      "name": "heat exchanger"
    },
    {
      "count": 1,
      "line_hits": [
        2417
      ],
      "name": "control rod"
    }
  ],
  "organization": [
    {
      "count": 5,
      "line_hits": [
        13,
        33,
        43,
        61,
        788
      ],
      "name": "ORNL"
    },
    {
      "count": 2,
      "line_hits": [
        587,
        589
      ],
      "name": "General Electric"
    },
    {
      "count": 2,
      "line_hits": [
        39,
        67
      ],
      "name": "Union Carbide"
    },
    {
      "count": 1,
      "line_hits": [
        195
      ],
      "name": "AEC"
    },
    {
      "count": 1,
      "line_hits": [
        191
      ],
      "name": "ANL"
    },
    {
      "count": 1,
      "line_hits": [
        1106
      ],
      "name": "Foster Wheeler"
    }
  ],
  "reactor": [
    {
      "count": 79,
      "line_hits": [
        740,
        758,
        762,
        766,
        778,
        784,
        786,
        788,
        790,
        806,
        823,
        845,
        848,
        858,
        866,
        870,
        874,
        896,
        902,
        924,
        939,
        941,
        943,
        945,
        951,
        953,
        970,
        974,
        986,
        1004,
        1010,
        1026,
        1028,
        1037,
        1045,
        1047,
        1049,
        1069,
        1072,
        1074,
        1170,
        1172,
        1182,
        1184,
        1186,
        1192,
        1204,
        1216,
        1225,
        1543
      ],
      "name": "ARE"
    },
    {
      "count": 1,
      "line_hits": [
        2419
      ],
      "name": "ART"
    }
  ],
  "report-series": [
    {
      "count": 1,
      "line_hits": [
        179
      ],
      "name": "ORNL Central Files"
    }
  ],
  "salt-system": [
    {
      "count": 3,
      "line_hits": [
        768,
        856,
        986
      ],
      "name": "UF4"
    },
    {
      "count": 3,
      "line_hits": [
        768,
        856,
        986
      ],
      "name": "fluoride salt"
    }
  ]
}